orange3_sqlquery-0.0.3.dist-info/licenses/LICENSE
orangecontrib/__init__.py
orangecontrib/sqlquery/__init__.py
orangecontrib/sqlquery/widgets/__init__.py
orangecontrib/sqlquery/widgets/owduckdbtable.py
orangecontrib/sqlquery/widgets/owsqlquery.py
orangecontrib/sqlquery/widgets/icons/DuckDB_logo.svg
orangecontrib/sqlquery/widgets/icons/sqlquery.svg
orange3_sqlquery-0.0.3.dist-info/METADATA
orange3_sqlquery-0.0.3.dist-info/WHEEL
orange3_sqlquery-0.0.3.dist-info/entry_points.txt
orange3_sqlquery-0.0.3.dist-info/top_level.txt
orange3_sqlquery-0.0.3.dist-info/RECORD
